zmprinter-0.1.5.dist-info/METADATA
zmprinter-0.1.5.dist-info/WHEEL
zmprinter-0.1.5.dist-info/entry_points.txt
zmprinter/__init__.py
zmprinter/config.py
zmprinter/core.py
zmprinter/elements.py
zmprinter/enums.py
zmprinter/exceptions.py
zmprinter/libs/AnyCPU/LabelPrinter.dll
zmprinter/libs/Readme.txt
zmprinter/libs/x64/LabelPrinter.dll
zmprinter/libs/x86/LabelPrinter.dll
zmprinter/utils.py
zmprinter-0.1.5.dist-info/RECORD
